[{"name": "박영진", "team": "삼성", "position": "P", "G": "1", "Inning": "1.0", "avg": ".600", "obp": ".667", "year": 1984}, {"name": "김일융", "team": "삼성", "position": "P", "G": "38", "Inning": "222.0", "avg": ".238", "obp": ".310", "year": 1984}, {"name": "성낙수", "team": "삼성", "position": "P", "G": "6", "Inning": "15.1", "avg": ".339", "obp": ".391", "year": 1984}, {"name": "황규봉", "team": "삼성", "position": "P", "G": "30", "Inning": "108.0", "avg": ".266", "obp": ".318", "year": 1984}, {"name": "전용권", "team": "삼성", "position": "P", "G": "13", "Inning": "26.1", "avg": ".268", "obp": ".351", "year": 1984}, {"name": "김시진", "team": "삼성", "position": "P", "G": "39", "Inning": "215.0", "avg": ".231", "obp": ".336", "year": 1984}, {"name": "권영호", "team": "삼성", "position": "P", "G": "29", "Inning": "137.1", "avg": ".251", "obp": ".332", "year": 1984}, {"name": "송진호", "team": "삼성", "position": "P", "G": "12", "Inning": "33.0", "avg": ".238", "obp": ".384", "year": 1984}, {"name": "이선희", "team": "삼성", "position": "P", "G": "17", "Inning": "51.2", "avg": ".305", "obp": ".380", "year": 1984}, {"name": "양일환", "team": "삼성", "position": "P", "G": "20", "Inning": "64.0", "avg": ".255", "obp": ".355", "year": 1984}, {"name": "진동한", "team": "삼성", "position": "P", "G": "2", "Inning": "5.0", "avg": ".063", "obp": ".286", "year": 1984}, {"name": "권기홍", "team": "삼성", "position": "P", "G": "3", "Inning": "8.0", "avg": ".281", "obp": ".378", "year": 1984}, {"name": "최동원", "team": "롯데", "position": "P", "G": "51", "Inning": "284.2", "avg": ".224", "obp": ".280", "year": 1984}, {"name": "배경환", "team": "롯데", "position": "P", "G": "35", "Inning": "121.2", "avg": ".283", "obp": ".328", "year": 1984}, {"name": "조용철", "team": "롯데", "position": "P", "G": "2", "Inning": "2.0", "avg": ".333", "obp": ".455", "year": 1984}, {"name": "천창호", "team": "롯데", "position": "P", "G": "18", "Inning": "47.0", "avg": ".302", "obp": ".377", "year": 1984}, {"name": "안창완", "team": "롯데", "position": "P", "G": "27", "Inning": "70.0", "avg": ".276", "obp": ".352", "year": 1984}, {"name": "임호균", "team": "롯데", "position": "P", "G": "27", "Inning": "161.2", "avg": ".253", "obp": ".343", "year": 1984}, {"name": "김재열", "team": "롯데", "position": "P", "G": "15", "Inning": "36.0", "avg": ".269", "obp": ".355", "year": 1984}, {"name": "이문한", "team": "롯데", "position": "P", "G": "16", "Inning": "50.0", "avg": ".283", "obp": ".345", "year": 1984}, {"name": "김문희", "team": "롯데", "position": "P", "G": "19", "Inning": "56.1", "avg": ".332", "obp": ".394", "year": 1984}, {"name": "이진우", "team": "롯데", "position": "P", "G": "10", "Inning": "22.1", "avg": ".269", "obp": ".333", "year": 1984}, {"name": "이윤섭", "team": "롯데", "position": "P", "G": "6", "Inning": "10.0", "avg": ".316", "obp": ".378", "year": 1984}, {"name": "박덕용", "team": "롯데", "position": "P", "G": "6", "Inning": "19.0", "avg": ".267", "obp": ".329", "year": 1984}, {"name": "문희수", "team": "해태", "position": "P", "G": "5", "Inning": "12.2", "avg": ".245", "obp": ".327", "year": 1984}, {"name": "김용남", "team": "해태", "position": "P", "G": "31", "Inning": "132.2", "avg": ".258", "obp": ".284", "year": 1984}, {"name": "방수원", "team": "해태", "position": "P", "G": "25", "Inning": "66.0", "avg": ".259", "obp": ".327", "year": 1984}, {"name": "주동식", "team": "해태", "position": "P", "G": "18", "Inning": "83.1", "avg": ".242", "obp": ".297", "year": 1984}, {"name": "이상윤", "team": "해태", "position": "P", "G": "40", "Inning": "211.2", "avg": ".242", "obp": ".314", "year": 1984}, {"name": "조도연", "team": "해태", "position": "P", "G": "35", "Inning": "129.1", "avg": ".256", "obp": ".318", "year": 1984}, {"name": "황기선", "team": "해태", "position": "P", "G": "38", "Inning": "124.1", "avg": ".238", "obp": ".329", "year": 1984}, {"name": "강만식", "team": "해태", "position": "P", "G": "28", "Inning": "129.2", "avg": ".253", "obp": ".312", "year": 1984}, {"name": "김현재", "team": "해태", "position": "P", "G": "4", "Inning": "6.2", "avg": ".286", "obp": ".400", "year": 1984}, {"name": "장명부", "team": "삼미", "position": "P", "G": "45", "Inning": "261.2", "avg": ".266", "obp": ".313", "year": 1984}, {"name": "최계훈", "team": "삼미", "position": "P", "G": "34", "Inning": "137.1", "avg": ".259", "obp": ".335", "year": 1984}, {"name": "감사용", "team": "삼미", "position": "P", "G": "1", "Inning": "2.1", "avg": ".250", "obp": ".333", "year": 1984}, {"name": "김상기", "team": "삼미", "position": "P", "G": "11", "Inning": "22.1", "avg": ".289", "obp": ".362", "year": 1984}, {"name": "박정후", "team": "삼미", "position": "P", "G": "31", "Inning": "139.0", "avg": ".264", "obp": ".365", "year": 1984}, {"name": "김재현", "team": "삼미", "position": "P", "G": "24", "Inning": "89.2", "avg": ".280", "obp": ".347", "year": 1984}, {"name": "김덕열", "team": "삼미", "position": "P", "G": "2", "Inning": "2.0", "avg": ".444", "obp": ".546", "year": 1984}, {"name": "정성만", "team": "삼미", "position": "P", "G": "29", "Inning": "150.0", "avg": ".263", "obp": ".361", "year": 1984}, {"name": "오문현", "team": "삼미", "position": "P", "G": "11", "Inning": "29.0", "avg": ".273", "obp": ".350", "year": 1984}, {"name": "신태중", "team": "삼미", "position": "P", "G": "14", "Inning": "48.1", "avg": ".301", "obp": ".413", "year": 1984}, {"name": "인호봉", "team": "삼미", "position": "P", "G": "8", "Inning": "17.2", "avg": ".226", "obp": ".395", "year": 1984}, {"name": "김봉근", "team": "MBC", "position": "P", "G": "32", "Inning": "171.1", "avg": ".233", "obp": ".281", "year": 1984}, {"name": "하기룡", "team": "MBC", "position": "P", "G": "30", "Inning": "178.2", "avg": ".259", "obp": ".329", "year": 1984}, {"name": "유종겸", "team": "MBC", "position": "P", "G": "38", "Inning": "183.2", "avg": ".260", "obp": ".315", "year": 1984}, {"name": "오영일", "team": "MBC", "position": "P", "G": "40", "Inning": "239.2", "avg": ".269", "obp": ".336", "year": 1984}, {"name": "이광권", "team": "MBC", "position": "P", "G": "13", "Inning": "50.1", "avg": ".296", "obp": ".376", "year": 1984}, {"name": "이길환", "team": "MBC", "position": "P", "G": "12", "Inning": "50.0", "avg": ".318", "obp": ".352", "year": 1984}, {"name": "정순명", "team": "MBC", "position": "P", "G": "8", "Inning": "22.2", "avg": ".276", "obp": ".400", "year": 1984}, {"name": "장호연", "team": "OB", "position": "P", "G": "31", "Inning": "102.1", "avg": ".215", "obp": ".290", "year": 1984}, {"name": "최일언", "team": "OB", "position": "P", "G": "37", "Inning": "167.2", "avg": ".240", "obp": ".319", "year": 1984}, {"name": "계형철", "team": "OB", "position": "P", "G": "29", "Inning": "174.2", "avg": ".217", "obp": ".295", "year": 1984}, {"name": "윤석환", "team": "OB", "position": "P", "G": "57", "Inning": "146.0", "avg": ".205", "obp": ".267", "year": 1984}, {"name": "황태환", "team": "OB", "position": "P", "G": "17", "Inning": "40.0", "avg": ".263", "obp": ".340", "year": 1984}, {"name": "박상열", "team": "OB", "position": "P", "G": "30", "Inning": "133.0", "avg": ".235", "obp": ".320", "year": 1984}, {"name": "김진욱", "team": "OB", "position": "P", "G": "25", "Inning": "118.0", "avg": ".248", "obp": ".349", "year": 1984}, {"name": "강철원", "team": "OB", "position": "P", "G": "3", "Inning": "3.2", "avg": ".286", "obp": ".389", "year": 1984}]