[{"name": "임치영", "team": "SK", "position": "P", "G": "1", "Inning": "1.0", "avg": ".500", "obp": ".500", "year": 2017}, {"name": "켈리", "team": "SK", "position": "P", "G": "30", "Inning": "190.0", "avg": ".272", "obp": ".321", "year": 2017}, {"name": "서진용", "team": "SK", "position": "P", "G": "42", "Inning": "46.0", "avg": ".249", "obp": ".337", "year": 2017}, {"name": "백인식", "team": "SK", "position": "P", "G": "11", "Inning": "18.2", "avg": ".231", "obp": ".324", "year": 2017}, {"name": "신재웅", "team": "SK", "position": "P", "G": "32", "Inning": "31.0", "avg": ".209", "obp": ".302", "year": 2017}, {"name": "전유수", "team": "SK", "position": "P", "G": "18", "Inning": "20.2", "avg": ".333", "obp": ".431", "year": 2017}, {"name": "문광은", "team": "SK", "position": "P", "G": "46", "Inning": "44.2", "avg": ".298", "obp": ".381", "year": 2017}, {"name": "김찬호", "team": "SK", "position": "P", "G": "5", "Inning": "5.1", "avg": ".417", "obp": ".533", "year": 2017}, {"name": "다이아몬드", "team": "SK", "position": "P", "G": "24", "Inning": "134.1", "avg": ".308", "obp": ".359", "year": 2017}, {"name": "채병용", "team": "SK", "position": "P", "G": "43", "Inning": "50.0", "avg": ".298", "obp": ".352", "year": 2017}, {"name": "윤희상", "team": "SK", "position": "P", "G": "23", "Inning": "120.0", "avg": ".307", "obp": ".361", "year": 2017}, {"name": "허건엽", "team": "SK", "position": "P", "G": "8", "Inning": "8.1", "avg": ".385", "obp": ".415", "year": 2017}, {"name": "박정배", "team": "SK", "position": "P", "G": "61", "Inning": "68.0", "avg": ".240", "obp": ".332", "year": 2017}, {"name": "임준혁", "team": "SK", "position": "P", "G": "43", "Inning": "45.1", "avg": ".294", "obp": ".396", "year": 2017}, {"name": "박종훈", "team": "SK", "position": "P", "G": "29", "Inning": "151.1", "avg": ".254", "obp": ".351", "year": 2017}, {"name": "김주한", "team": "SK", "position": "P", "G": "63", "Inning": "69.2", "avg": ".297", "obp": ".379", "year": 2017}, {"name": "김정빈", "team": "SK", "position": "P", "G": "2", "Inning": "3.0", "avg": ".182", "obp": ".400", "year": 2017}, {"name": "김대유", "team": "SK", "position": "P", "G": "6", "Inning": "4.2", "avg": ".381", "obp": ".417", "year": 2017}, {"name": "문승원", "team": "SK", "position": "P", "G": "29", "Inning": "155.1", "avg": ".294", "obp": ".359", "year": 2017}, {"name": "김태훈", "team": "SK", "position": "P", "G": "21", "Inning": "41.1", "avg": ".337", "obp": ".407", "year": 2017}, {"name": "박희수", "team": "SK", "position": "P", "G": "48", "Inning": "38.0", "avg": ".310", "obp": ".398", "year": 2017}, {"name": "김성민", "team": "SK", "position": "P", "G": "10", "Inning": "11.2", "avg": ".320", "obp": ".424", "year": 2017}, {"name": "정동윤", "team": "SK", "position": "P", "G": "2", "Inning": "3.0", "avg": ".385", "obp": ".467", "year": 2017}, {"name": "정영일", "team": "SK", "position": "P", "G": "9", "Inning": "8.0", "avg": ".324", "obp": ".432", "year": 2017}, {"name": "이건욱", "team": "SK", "position": "P", "G": "2", "Inning": "1.1", "avg": ".500", "obp": ".636", "year": 2017}, {"name": "장지훈", "team": "삼성", "position": "P", "G": "4", "Inning": "2.1", "avg": ".222", "obp": ".300", "year": 2017}, {"name": "장필준", "team": "삼성", "position": "P", "G": "56", "Inning": "67.1", "avg": ".300", "obp": ".368", "year": 2017}, {"name": "백정현", "team": "삼성", "position": "P", "G": "35", "Inning": "100.2", "avg": ".279", "obp": ".344", "year": 2017}, {"name": "장원삼", "team": "삼성", "position": "P", "G": "49", "Inning": "67.1", "avg": ".342", "obp": ".384", "year": 2017}, {"name": "임현준", "team": "삼성", "position": "P", "G": "11", "Inning": "10.2", "avg": ".275", "obp": ".362", "year": 2017}, {"name": "윤성환", "team": "삼성", "position": "P", "G": "28", "Inning": "174.1", "avg": ".271", "obp": ".321", "year": 2017}, {"name": "심창민", "team": "삼성", "position": "P", "G": "66", "Inning": "75.1", "avg": ".199", "obp": ".323", "year": 2017}, {"name": "우규민", "team": "삼성", "position": "P", "G": "27", "Inning": "133.0", "avg": ".300", "obp": ".343", "year": 2017}, {"name": "이수민", "team": "삼성", "position": "P", "G": "1", "Inning": "2.2", "avg": ".333", "obp": ".429", "year": 2017}, {"name": "권오준", "team": "삼성", "position": "P", "G": "45", "Inning": "56.0", "avg": ".281", "obp": ".332", "year": 2017}, {"name": "김동호", "team": "삼성", "position": "P", "G": "20", "Inning": "36.0", "avg": ".349", "obp": ".444", "year": 2017}, {"name": "페트릭", "team": "삼성", "position": "P", "G": "25", "Inning": "134.0", "avg": ".314", "obp": ".377", "year": 2017}, {"name": "최지광", "team": "삼성", "position": "P", "G": "11", "Inning": "25.0", "avg": ".289", "obp": ".418", "year": 2017}, {"name": "최충연", "team": "삼성", "position": "P", "G": "42", "Inning": "84.0", "avg": ".312", "obp": ".406", "year": 2017}, {"name": "김대우", "team": "삼성", "position": "P", "G": "25", "Inning": "50.0", "avg": ".343", "obp": ".427", "year": 2017}, {"name": "박근홍", "team": "삼성", "position": "P", "G": "24", "Inning": "15.1", "avg": ".232", "obp": ".400", "year": 2017}, {"name": "김승현", "team": "삼성", "position": "P", "G": "41", "Inning": "43.2", "avg": ".298", "obp": ".427", "year": 2017}, {"name": "황수범", "team": "삼성", "position": "P", "G": "10", "Inning": "31.1", "avg": ".336", "obp": ".426", "year": 2017}, {"name": "김시현", "team": "삼성", "position": "P", "G": "17", "Inning": "21.1", "avg": ".349", "obp": ".447", "year": 2017}, {"name": "정인욱", "team": "삼성", "position": "P", "G": "9", "Inning": "32.0", "avg": ".333", "obp": ".408", "year": 2017}, {"name": "안성무", "team": "삼성", "position": "P", "G": "5", "Inning": "11.2", "avg": ".311", "obp": ".431", "year": 2017}, {"name": "레나도", "team": "삼성", "position": "P", "G": "11", "Inning": "49.0", "avg": ".342", "obp": ".427", "year": 2017}, {"name": "임대한", "team": "삼성", "position": "P", "G": "12", "Inning": "14.0", "avg": ".394", "obp": ".506", "year": 2017}, {"name": "김현우", "team": "삼성", "position": "P", "G": "8", "Inning": "10.2", "avg": ".326", "obp": ".392", "year": 2017}, {"name": "이승현", "team": "삼성", "position": "P", "G": "30", "Inning": "31.2", "avg": ".277", "obp": ".381", "year": 2017}, {"name": "안규현", "team": "삼성", "position": "P", "G": "1", "Inning": "2.0", "avg": ".286", "obp": ".546", "year": 2017}, {"name": "원종현", "team": "NC", "position": "P", "G": "68", "Inning": "80.0", "avg": ".273", "obp": ".327", "year": 2017}, {"name": "류재인", "team": "NC", "position": "P", "G": "1", "Inning": "0.2", "avg": ".333", "obp": ".333", "year": 2017}, {"name": "맨쉽", "team": "NC", "position": "P", "G": "21", "Inning": "112.2", "avg": ".260", "obp": ".323", "year": 2017}, {"name": "강장산", "team": "NC", "position": "P", "G": "5", "Inning": "11.1", "avg": ".214", "obp": ".306", "year": 2017}, {"name": "김진성", "team": "NC", "position": "P", "G": "69", "Inning": "89.2", "avg": ".220", "obp": ".281", "year": 2017}, {"name": "이민호", "team": "NC", "position": "P", "G": "60", "Inning": "88.2", "avg": ".258", "obp": ".328", "year": 2017}, {"name": "임정호", "team": "NC", "position": "P", "G": "59", "Inning": "30.1", "avg": ".256", "obp": ".343", "year": 2017}, {"name": "해커", "team": "NC", "position": "P", "G": "26", "Inning": "160.1", "avg": ".259", "obp": ".307", "year": 2017}, {"name": "임창민", "team": "NC", "position": "P", "G": "60", "Inning": "66.0", "avg": ".246", "obp": ".312", "year": 2017}, {"name": "윤수호", "team": "NC", "position": "P", "G": "40", "Inning": "47.0", "avg": ".234", "obp": ".356", "year": 2017}, {"name": "구창모", "team": "NC", "position": "P", "G": "31", "Inning": "115.0", "avg": ".299", "obp": ".373", "year": 2017}, {"name": "장현식", "team": "NC", "position": "P", "G": "31", "Inning": "134.1", "avg": ".268", "obp": ".354", "year": 2017}, {"name": "민태호", "team": "NC", "position": "P", "G": "7", "Inning": "8.2", "avg": ".294", "obp": ".385", "year": 2017}, {"name": "이형범", "team": "NC", "position": "P", "G": "14", "Inning": "29.1", "avg": ".245", "obp": ".349", "year": 2017}, {"name": "이재학", "team": "NC", "position": "P", "G": "28", "Inning": "119.0", "avg": ".295", "obp": ".366", "year": 2017}, {"name": "최금강", "team": "NC", "position": "P", "G": "39", "Inning": "89.2", "avg": ".305", "obp": ".381", "year": 2017}, {"name": "강윤구", "team": "NC", "position": "P", "G": "36", "Inning": "54.2", "avg": ".264", "obp": ".340", "year": 2017}, {"name": "정수민", "team": "NC", "position": "P", "G": "15", "Inning": "28.0", "avg": ".282", "obp": ".378", "year": 2017}, {"name": "최성영", "team": "NC", "position": "P", "G": "7", "Inning": "11.1", "avg": ".354", "obp": ".456", "year": 2017}, {"name": "배재환", "team": "NC", "position": "P", "G": "3", "Inning": "8.0", "avg": ".382", "obp": ".475", "year": 2017}, {"name": "송신영", "team": "한화", "position": "P", "G": "5", "Inning": "6.1", "avg": ".250", "obp": ".308", "year": 2017}, {"name": "김진영", "team": "한화", "position": "P", "G": "3", "Inning": "2.2", "avg": ".385", "obp": ".467", "year": 2017}, {"name": "정우람", "team": "한화", "position": "P", "G": "56", "Inning": "59.0", "avg": ".214", "obp": ".287", "year": 2017}, {"name": "김경태", "team": "한화", "position": "P", "G": "19", "Inning": "12.2", "avg": ".261", "obp": ".404", "year": 2017}, {"name": "강승현", "team": "한화", "position": "P", "G": "31", "Inning": "38.1", "avg": ".282", "obp": ".343", "year": 2017}, {"name": "오간도", "team": "한화", "position": "P", "G": "19", "Inning": "110.0", "avg": ".270", "obp": ".332", "year": 2017}, {"name": "비야누에바", "team": "한화", "position": "P", "G": "20", "Inning": "112.0", "avg": ".256", "obp": ".298", "year": 2017}, {"name": "심수창", "team": "한화", "position": "P", "G": "48", "Inning": "57.0", "avg": ".307", "obp": ".371", "year": 2017}, {"name": "박정진", "team": "한화", "position": "P", "G": "55", "Inning": "48.0", "avg": ".222", "obp": ".323", "year": 2017}, {"name": "이동걸", "team": "한화", "position": "P", "G": "24", "Inning": "36.2", "avg": ".261", "obp": ".301", "year": 2017}, {"name": "김재영", "team": "한화", "position": "P", "G": "20", "Inning": "85.1", "avg": ".310", "obp": ".363", "year": 2017}, {"name": "배영수", "team": "한화", "position": "P", "G": "25", "Inning": "128.0", "avg": ".298", "obp": ".348", "year": 2017}, {"name": "정재원", "team": "한화", "position": "P", "G": "14", "Inning": "21.0", "avg": ".284", "obp": ".398", "year": 2017}, {"name": "안영명", "team": "한화", "position": "P", "G": "25", "Inning": "87.2", "avg": ".336", "obp": ".386", "year": 2017}, {"name": "박상원", "team": "한화", "position": "P", "G": "18", "Inning": "21.2", "avg": ".241", "obp": ".302", "year": 2017}, {"name": "서균", "team": "한화", "position": "P", "G": "14", "Inning": "14.1", "avg": ".298", "obp": ".365", "year": 2017}, {"name": "윤규진", "team": "한화", "position": "P", "G": "36", "Inning": "119.0", "avg": ".297", "obp": ".356", "year": 2017}, {"name": "송창식", "team": "한화", "position": "P", "G": "63", "Inning": "73.1", "avg": ".268", "obp": ".353", "year": 2017}, {"name": "장민재", "team": "한화", "position": "P", "G": "33", "Inning": "62.2", "avg": ".349", "obp": ".397", "year": 2017}, {"name": "송은범", "team": "한화", "position": "P", "G": "13", "Inning": "37.1", "avg": ".304", "obp": ".406", "year": 2017}, {"name": "권혁", "team": "한화", "position": "P", "G": "37", "Inning": "31.1", "avg": ".305", "obp": ".371", "year": 2017}, {"name": "이태양", "team": "한화", "position": "P", "G": "16", "Inning": "59.0", "avg": ".326", "obp": ".393", "year": 2017}, {"name": "김민우", "team": "한화", "position": "P", "G": "4", "Inning": "7.1", "avg": ".541", "obp": ".630", "year": 2017}, {"name": "김범수", "team": "한화", "position": "P", "G": "15", "Inning": "31.0", "avg": ".336", "obp": ".449", "year": 2017}, {"name": "이충호", "team": "한화", "position": "P", "G": "21", "Inning": "11.1", "avg": ".412", "obp": ".537", "year": 2017}, {"name": "손주영", "team": "LG", "position": "P", "G": "5", "Inning": "6.0", "avg": ".261", "obp": ".308", "year": 2017}, {"name": "허프", "team": "LG", "position": "P", "G": "19", "Inning": "124.2", "avg": ".215", "obp": ".239", "year": 2017}, {"name": "소사", "team": "LG", "position": "P", "G": "30", "Inning": "185.1", "avg": ".264", "obp": ".301", "year": 2017}, {"name": "이동현", "team": "LG", "position": "P", "G": "45", "Inning": "50.2", "avg": ".278", "obp": ".322", "year": 2017}, {"name": "임정우", "team": "LG", "position": "P", "G": "17", "Inning": "16.2", "avg": ".230", "obp": ".309", "year": 2017}, {"name": "여건욱", "team": "LG", "position": "P", "G": "3", "Inning": "3.1", "avg": ".286", "obp": ".412", "year": 2017}, {"name": "정찬헌", "team": "LG", "position": "P", "G": "61", "Inning": "61.2", "avg": ".311", "obp": ".380", "year": 2017}, {"name": "신승현", "team": "LG", "position": "P", "G": "3", "Inning": "3.2", "avg": ".100", "obp": ".167", "year": 2017}, {"name": "차우찬", "team": "LG", "position": "P", "G": "28", "Inning": "175.2", "avg": ".252", "obp": ".297", "year": 2017}, {"name": "신정락", "team": "LG", "position": "P", "G": "63", "Inning": "59.0", "avg": ".271", "obp": ".361", "year": 2017}, {"name": "진해수", "team": "LG", "position": "P", "G": "75", "Inning": "52.2", "avg": ".267", "obp": ".318", "year": 2017}, {"name": "고우석", "team": "LG", "position": "P", "G": "25", "Inning": "26.0", "avg": ".291", "obp": ".364", "year": 2017}, {"name": "류제국", "team": "LG", "position": "P", "G": "25", "Inning": "131.1", "avg": ".274", "obp": ".364", "year": 2017}, {"name": "임찬규", "team": "LG", "position": "P", "G": "27", "Inning": "124.1", "avg": ".277", "obp": ".364", "year": 2017}, {"name": "윤지웅", "team": "LG", "position": "P", "G": "34", "Inning": "35.0", "avg": ".287", "obp": ".349", "year": 2017}, {"name": "최성훈", "team": "LG", "position": "P", "G": "32", "Inning": "22.0", "avg": ".272", "obp": ".374", "year": 2017}, {"name": "유원상", "team": "LG", "position": "P", "G": "6", "Inning": "7.1", "avg": ".286", "obp": ".389", "year": 2017}, {"name": "김대현", "team": "LG", "position": "P", "G": "26", "Inning": "94.0", "avg": ".270", "obp": ".339", "year": 2017}, {"name": "유재유", "team": "LG", "position": "P", "G": "3", "Inning": "5.0", "avg": ".286", "obp": ".400", "year": 2017}, {"name": "김지용", "team": "LG", "position": "P", "G": "53", "Inning": "53.0", "avg": ".278", "obp": ".323", "year": 2017}, {"name": "최동환", "team": "LG", "position": "P", "G": "35", "Inning": "38.0", "avg": ".262", "obp": ".347", "year": 2017}, {"name": "배민관", "team": "LG", "position": "P", "G": "4", "Inning": "3.2", "avg": ".400", "obp": ".526", "year": 2017}, {"name": "차재용", "team": "롯데", "position": "P", "G": "3", "Inning": "2.1", "avg": ".125", "obp": ".125", "year": 2017}, {"name": "강영식", "team": "롯데", "position": "P", "G": "4", "Inning": "2.1", "avg": ".333", "obp": ".385", "year": 2017}, {"name": "조정훈", "team": "롯데", "position": "P", "G": "26", "Inning": "23.0", "avg": ".200", "obp": ".306", "year": 2017}, {"name": "손승락", "team": "롯데", "position": "P", "G": "61", "Inning": "62.0", "avg": ".251", "obp": ".286", "year": 2017}, {"name": "진명호", "team": "롯데", "position": "P", "G": "4", "Inning": "5.0", "avg": ".067", "obp": ".300", "year": 2017}, {"name": "윤길현", "team": "롯데", "position": "P", "G": "40", "Inning": "39.1", "avg": ".293", "obp": ".374", "year": 2017}, {"name": "린드블럼", "team": "롯데", "position": "P", "G": "12", "Inning": "72.2", "avg": ".244", "obp": ".293", "year": 2017}, {"name": "레일리", "team": "롯데", "position": "P", "G": "30", "Inning": "187.1", "avg": ".274", "obp": ".328", "year": 2017}, {"name": "박진형", "team": "롯데", "position": "P", "G": "45", "Inning": "88.0", "avg": ".267", "obp": ".363", "year": 2017}, {"name": "애디튼", "team": "롯데", "position": "P", "G": "15", "Inning": "70.0", "avg": ".299", "obp": ".361", "year": 2017}, {"name": "송승준", "team": "롯데", "position": "P", "G": "30", "Inning": "130.1", "avg": ".260", "obp": ".318", "year": 2017}, {"name": "김유영", "team": "롯데", "position": "P", "G": "40", "Inning": "48.2", "avg": ".281", "obp": ".370", "year": 2017}, {"name": "박세웅", "team": "롯데", "position": "P", "G": "28", "Inning": "171.1", "avg": ".263", "obp": ".328", "year": 2017}, {"name": "배장호", "team": "롯데", "position": "P", "G": "72", "Inning": "66.1", "avg": ".275", "obp": ".340", "year": 2017}, {"name": "이명우", "team": "롯데", "position": "P", "G": "34", "Inning": "26.2", "avg": ".304", "obp": ".353", "year": 2017}, {"name": "장시환", "team": "롯데", "position": "P", "G": "48", "Inning": "45.0", "avg": ".256", "obp": ".373", "year": 2017}, {"name": "김원중", "team": "롯데", "position": "P", "G": "24", "Inning": "107.1", "avg": ".304", "obp": ".390", "year": 2017}, {"name": "강동호", "team": "롯데", "position": "P", "G": "27", "Inning": "41.1", "avg": ".269", "obp": ".337", "year": 2017}, {"name": "이정민", "team": "롯데", "position": "P", "G": "24", "Inning": "26.2", "avg": ".308", "obp": ".374", "year": 2017}, {"name": "박시영", "team": "롯데", "position": "P", "G": "47", "Inning": "57.0", "avg": ".268", "obp": ".359", "year": 2017}, {"name": "노경은", "team": "롯데", "position": "P", "G": "9", "Inning": "14.2", "avg": ".391", "obp": ".447", "year": 2017}, {"name": "김세현", "team": "KIA", "position": "P", "G": "21", "Inning": "21.0", "avg": ".274", "obp": ".311", "year": 2017}, {"name": "임창용", "team": "KIA", "position": "P", "G": "51", "Inning": "50.0", "avg": ".263", "obp": ".350", "year": 2017}, {"name": "양현종", "team": "KIA", "position": "P", "G": "31", "Inning": "193.1", "avg": ".278", "obp": ".317", "year": 2017}, {"name": "임기영", "team": "KIA", "position": "P", "G": "23", "Inning": "118.1", "avg": ".294", "obp": ".327", "year": 2017}, {"name": "김명찬", "team": "KIA", "position": "P", "G": "6", "Inning": "5.0", "avg": ".263", "obp": ".333", "year": 2017}, {"name": "심동섭", "team": "KIA", "position": "P", "G": "52", "Inning": "50.2", "avg": ".311", "obp": ".371", "year": 2017}, {"name": "고효준", "team": "KIA", "position": "P", "G": "40", "Inning": "40.0", "avg": ".280", "obp": ".386", "year": 2017}, {"name": "헥터", "team": "KIA", "position": "P", "G": "30", "Inning": "201.2", "avg": ".279", "obp": ".319", "year": 2017}, {"name": "최영필", "team": "KIA", "position": "P", "G": "2", "Inning": "1.1", "avg": ".625", "obp": ".600", "year": 2017}, {"name": "박경태", "team": "KIA", "position": "P", "G": "3", "Inning": "4.0", "avg": ".350", "obp": ".417", "year": 2017}, {"name": "이민우", "team": "KIA", "position": "P", "G": "4", "Inning": "12.2", "avg": ".269", "obp": ".283", "year": 2017}, {"name": "한승혁", "team": "KIA", "position": "P", "G": "36", "Inning": "39.0", "avg": ".297", "obp": ".380", "year": 2017}, {"name": "홍건희", "team": "KIA", "position": "P", "G": "31", "Inning": "59.0", "avg": ".346", "obp": ".397", "year": 2017}, {"name": "팻딘", "team": "KIA", "position": "P", "G": "30", "Inning": "176.0", "avg": ".304", "obp": ".352", "year": 2017}, {"name": "임기준", "team": "KIA", "position": "P", "G": "15", "Inning": "22.0", "avg": ".284", "obp": ".388", "year": 2017}, {"name": "박지훈", "team": "KIA", "position": "P", "G": "18", "Inning": "14.0", "avg": ".291", "obp": ".394", "year": 2017}, {"name": "박진태", "team": "KIA", "position": "P", "G": "38", "Inning": "57.2", "avg": ".319", "obp": ".389", "year": 2017}, {"name": "김윤동", "team": "KIA", "position": "P", "G": "65", "Inning": "80.1", "avg": ".234", "obp": ".346", "year": 2017}, {"name": "정용운", "team": "KIA", "position": "P", "G": "25", "Inning": "59.1", "avg": ".255", "obp": ".372", "year": 2017}, {"name": "남재현", "team": "KIA", "position": "P", "G": "9", "Inning": "7.2", "avg": ".421", "obp": ".521", "year": 2017}, {"name": "김진우", "team": "KIA", "position": "P", "G": "14", "Inning": "36.1", "avg": ".347", "obp": ".453", "year": 2017}, {"name": "손영민", "team": "KIA", "position": "P", "G": "15", "Inning": "13.1", "avg": ".426", "obp": ".462", "year": 2017}, {"name": "김광수", "team": "KIA", "position": "P", "G": "19", "Inning": "20.2", "avg": ".379", "obp": ".409", "year": 2017}, {"name": "정동현", "team": "KIA", "position": "P", "G": "1", "Inning": "2.1", "avg": ".417", "obp": ".500", "year": 2017}, {"name": "배힘찬", "team": "KIA", "position": "P", "G": "2", "Inning": "3.1", "avg": ".571", "obp": ".571", "year": 2017}, {"name": "김종훈", "team": "KIA", "position": "P", "G": "1", "Inning": "1.0", "avg": ".571", "obp": ".667", "year": 2017}, {"name": "김재윤", "team": "kt", "position": "P", "G": "41", "Inning": "37.1", "avg": ".283", "obp": ".333", "year": 2017}, {"name": "장시환", "team": "kt", "position": "P", "G": "5", "Inning": "6.1", "avg": ".227", "obp": ".308", "year": 2017}, {"name": "이상화", "team": "kt", "position": "P", "G": "70", "Inning": "66.0", "avg": ".273", "obp": ".325", "year": 2017}, {"name": "김도영", "team": "kt", "position": "P", "G": "1", "Inning": "1.0", "avg": ".250", "obp": ".250", "year": 2017}, {"name": "고영표", "team": "kt", "position": "P", "G": "25", "Inning": "141.2", "avg": ".299", "obp": ".337", "year": 2017}, {"name": "피어밴드", "team": "kt", "position": "P", "G": "26", "Inning": "160.0", "avg": ".251", "obp": ".294", "year": 2017}, {"name": "엄상백", "team": "kt", "position": "P", "G": "52", "Inning": "52.0", "avg": ".242", "obp": ".327", "year": 2017}, {"name": "박세진", "team": "kt", "position": "P", "G": "4", "Inning": "11.1", "avg": ".340", "obp": ".429", "year": 2017}, {"name": "조무근", "team": "kt", "position": "P", "G": "16", "Inning": "14.2", "avg": ".323", "obp": ".357", "year": 2017}, {"name": "심재민", "team": "kt", "position": "P", "G": "64", "Inning": "74.2", "avg": ".289", "obp": ".359", "year": 2017}, {"name": "로치", "team": "kt", "position": "P", "G": "28", "Inning": "165.0", "avg": ".304", "obp": ".371", "year": 2017}, {"name": "김사율", "team": "kt", "position": "P", "G": "19", "Inning": "34.2", "avg": ".336", "obp": ".370", "year": 2017}, {"name": "배우열", "team": "kt", "position": "P", "G": "26", "Inning": "34.1", "avg": ".363", "obp": ".408", "year": 2017}, {"name": "정성곤", "team": "kt", "position": "P", "G": "26", "Inning": "107.2", "avg": ".333", "obp": ".391", "year": 2017}, {"name": "윤근영", "team": "kt", "position": "P", "G": "12", "Inning": "18.0", "avg": ".324", "obp": ".368", "year": 2017}, {"name": "주권", "team": "kt", "position": "P", "G": "39", "Inning": "81.2", "avg": ".306", "obp": ".370", "year": 2017}, {"name": "배제성", "team": "kt", "position": "P", "G": "21", "Inning": "32.0", "avg": ".338", "obp": ".441", "year": 2017}, {"name": "홍성용", "team": "kt", "position": "P", "G": "37", "Inning": "39.0", "avg": ".290", "obp": ".366", "year": 2017}, {"name": "조근종", "team": "kt", "position": "P", "G": "1", "Inning": "2.0", "avg": ".500", "obp": ".539", "year": 2017}, {"name": "정대현", "team": "kt", "position": "P", "G": "12", "Inning": "53.1", "avg": ".338", "obp": ".390", "year": 2017}, {"name": "이종혁", "team": "kt", "position": "P", "G": "16", "Inning": "19.0", "avg": ".309", "obp": ".417", "year": 2017}, {"name": "홍성무", "team": "kt", "position": "P", "G": "7", "Inning": "6.1", "avg": ".393", "obp": ".500", "year": 2017}, {"name": "류희운", "team": "kt", "position": "P", "G": "24", "Inning": "81.0", "avg": ".303", "obp": ".409", "year": 2017}, {"name": "강장산", "team": "kt", "position": "P", "G": "12", "Inning": "15.0", "avg": ".327", "obp": ".443", "year": 2017}, {"name": "최원재", "team": "kt", "position": "P", "G": "4", "Inning": "2.0", "avg": ".600", "obp": ".667", "year": 2017}, {"name": "김정인", "team": "히어로즈", "position": "P", "G": "13", "Inning": "13.2", "avg": ".328", "obp": ".375", "year": 2017}, {"name": "조상우", "team": "히어로즈", "position": "P", "G": "13", "Inning": "44.1", "avg": ".298", "obp": ".352", "year": 2017}, {"name": "김세현", "team": "히어로즈", "position": "P", "G": "48", "Inning": "50.0", "avg": ".310", "obp": ".360", "year": 2017}, {"name": "밴헤켄", "team": "히어로즈", "position": "P", "G": "24", "Inning": "138.1", "avg": ".260", "obp": ".314", "year": 2017}, {"name": "김세현", "team": "히어로즈", "position": "P", "G": "27", "Inning": "29.0", "avg": ".333", "obp": ".391", "year": 2017}, {"name": "김홍빈", "team": "히어로즈", "position": "P", "G": "3", "Inning": "7.1", "avg": ".469", "obp": ".514", "year": 2017}, {"name": "김상수", "team": "히어로즈", "position": "P", "G": "60", "Inning": "61.1", "avg": ".253", "obp": ".323", "year": 2017}, {"name": "최원태", "team": "히어로즈", "position": "P", "G": "25", "Inning": "149.1", "avg": ".276", "obp": ".328", "year": 2017}, {"name": "오주원", "team": "히어로즈", "position": "P", "G": "57", "Inning": "73.2", "avg": ".312", "obp": ".346", "year": 2017}, {"name": "브리검", "team": "히어로즈", "position": "P", "G": "24", "Inning": "144.0", "avg": ".289", "obp": ".333", "year": 2017}, {"name": "이보근", "team": "히어로즈", "position": "P", "G": "55", "Inning": "52.2", "avg": ".290", "obp": ".338", "year": 2017}, {"name": "손동욱", "team": "히어로즈", "position": "P", "G": "1", "Inning": "1.0", "avg": ".000", "obp": ".250", "year": 2017}, {"name": "금민철", "team": "히어로즈", "position": "P", "G": "36", "Inning": "54.0", "avg": ".351", "obp": ".437", "year": 2017}, {"name": "한현희", "team": "히어로즈", "position": "P", "G": "38", "Inning": "106.2", "avg": ".254", "obp": ".306", "year": 2017}, {"name": "이영준", "team": "히어로즈", "position": "P", "G": "10", "Inning": "8.1", "avg": ".286", "obp": ".381", "year": 2017}, {"name": "신재영", "team": "히어로즈", "position": "P", "G": "34", "Inning": "125.0", "avg": ".282", "obp": ".335", "year": 2017}, {"name": "윤영삼", "team": "히어로즈", "position": "P", "G": "28", "Inning": "49.2", "avg": ".321", "obp": ".370", "year": 2017}, {"name": "김성민", "team": "히어로즈", "position": "P", "G": "23", "Inning": "76.0", "avg": ".287", "obp": ".366", "year": 2017}, {"name": "양훈", "team": "히어로즈", "position": "P", "G": "7", "Inning": "16.1", "avg": ".353", "obp": ".413", "year": 2017}, {"name": "김건태", "team": "히어로즈", "position": "P", "G": "5", "Inning": "6.0", "avg": ".448", "obp": ".484", "year": 2017}, {"name": "김성민", "team": "히어로즈", "position": "P", "G": "33", "Inning": "87.2", "avg": ".291", "obp": ".374", "year": 2017}, {"name": "박종윤", "team": "히어로즈", "position": "P", "G": "1", "Inning": "4.0", "avg": ".267", "obp": ".421", "year": 2017}, {"name": "정대현", "team": "히어로즈", "position": "P", "G": "5", "Inning": "13.0", "avg": ".306", "obp": ".370", "year": 2017}, {"name": "하영민", "team": "히어로즈", "position": "P", "G": "28", "Inning": "45.1", "avg": ".287", "obp": ".394", "year": 2017}, {"name": "정대현", "team": "히어로즈", "position": "P", "G": "17", "Inning": "66.1", "avg": ".332", "obp": ".386", "year": 2017}, {"name": "오윤성", "team": "히어로즈", "position": "P", "G": "6", "Inning": "7.2", "avg": ".281", "obp": ".452", "year": 2017}, {"name": "오설리반", "team": "히어로즈", "position": "P", "G": "3", "Inning": "8.0", "avg": ".425", "obp": ".465", "year": 2017}, {"name": "박정준", "team": "히어로즈", "position": "P", "G": "4", "Inning": "4.2", "avg": ".316", "obp": ".409", "year": 2017}, {"name": "황덕균", "team": "히어로즈", "position": "P", "G": "13", "Inning": "15.0", "avg": ".382", "obp": ".425", "year": 2017}, {"name": "마정길", "team": "히어로즈", "position": "P", "G": "7", "Inning": "10.1", "avg": ".326", "obp": ".380", "year": 2017}, {"name": "전용훈", "team": "두산", "position": "P", "G": "7", "Inning": "9.0", "avg": ".306", "obp": ".333", "year": 2017}, {"name": "김명신", "team": "두산", "position": "P", "G": "39", "Inning": "45.1", "avg": ".303", "obp": ".369", "year": 2017}, {"name": "함덕주", "team": "두산", "position": "P", "G": "35", "Inning": "137.1", "avg": ".247", "obp": ".333", "year": 2017}, {"name": "김강률", "team": "두산", "position": "P", "G": "70", "Inning": "89.0", "avg": ".263", "obp": ".329", "year": 2017}, {"name": "이현승", "team": "두산", "position": "P", "G": "57", "Inning": "52.0", "avg": ".302", "obp": ".360", "year": 2017}, {"name": "장원준", "team": "두산", "position": "P", "G": "29", "Inning": "180.1", "avg": ".253", "obp": ".316", "year": 2017}, {"name": "이용찬", "team": "두산", "position": "P", "G": "68", "Inning": "71.2", "avg": ".286", "obp": ".354", "year": 2017}, {"name": "김승회", "team": "두산", "position": "P", "G": "69", "Inning": "69.0", "avg": ".312", "obp": ".365", "year": 2017}, {"name": "장민익", "team": "두산", "position": "P", "G": "3", "Inning": "2.0", "avg": ".000", "obp": ".250", "year": 2017}, {"name": "임진우", "team": "두산", "position": "P", "G": "1", "Inning": "1.0", "avg": ".667", "obp": ".625", "year": 2017}, {"name": "유희관", "team": "두산", "position": "P", "G": "30", "Inning": "188.2", "avg": ".304", "obp": ".345", "year": 2017}, {"name": "니퍼트", "team": "두산", "position": "P", "G": "30", "Inning": "179.2", "avg": ".257", "obp": ".340", "year": 2017}, {"name": "고원준", "team": "두산", "position": "P", "G": "5", "Inning": "9.1", "avg": ".395", "obp": ".481", "year": 2017}, {"name": "박치국", "team": "두산", "position": "P", "G": "21", "Inning": "32.0", "avg": ".291", "obp": ".385", "year": 2017}, {"name": "김성배", "team": "두산", "position": "P", "G": "45", "Inning": "44.0", "avg": ".277", "obp": ".330", "year": 2017}, {"name": "보우덴", "team": "두산", "position": "P", "G": "17", "Inning": "87.1", "avg": ".265", "obp": ".347", "year": 2017}, {"name": "이현호", "team": "두산", "position": "P", "G": "24", "Inning": "30.0", "avg": ".361", "obp": ".422", "year": 2017}, {"name": "성영훈", "team": "두산", "position": "P", "G": "1", "Inning": "1.0", "avg": ".000", "obp": ".250", "year": 2017}, {"name": "고봉재", "team": "두산", "position": "P", "G": "1", "Inning": "1.0", "avg": ".500", "obp": ".600", "year": 2017}, {"name": "안규영", "team": "두산", "position": "P", "G": "5", "Inning": "5.1", "avg": ".318", "obp": ".484", "year": 2017}, {"name": "홍상삼", "team": "두산", "position": "P", "G": "11", "Inning": "17.0", "avg": ".290", "obp": ".398", "year": 2017}, {"name": "이영하", "team": "두산", "position": "P", "G": "20", "Inning": "35.2", "avg": ".316", "obp": ".392", "year": 2017}, {"name": "이용호", "team": "두산", "position": "P", "G": "1", "Inning": "0.1", "avg": "1.000", "obp": "1.000", "year": 2017}, {"name": "조승수", "team": "두산", "position": "P", "G": "1", "Inning": "0.0", "avg": "", "obp": "1.000", "year": 2017}]