[{"name": "박재홍", "team": "SK", "position": "CF", "avg": ".304", "obp": ".400", "slg": ".487", "total_hit": "128", "double_hit": "21", "triple_hit": "1", "home_run": "18", "BB": "67", "SB": "22", "Dead_Ball": "2", "one_hit": 88}, {"name": "김재현", "team": "SK", "position": "DH", "avg": ".315", "obp": ".445", "slg": ".500", "total_hit": "126", "double_hit": "17", "triple_hit": "0", "home_run": "19", "BB": "80", "SB": "2", "Dead_Ball": "16", "one_hit": 90}, {"name": "이진영", "team": "SK", "position": "RF", "avg": ".291", "obp": ".369", "slg": ".470", "total_hit": "132", "double_hit": "19", "triple_hit": "1", "home_run": "20", "BB": "55", "SB": "8", "Dead_Ball": "3", "one_hit": 92}, {"name": "이호준", "team": "SK", "position": "1B", "avg": ".271", "obp": ".367", "slg": ".500", "total_hit": "96", "double_hit": "16", "triple_hit": "1", "home_run": "21", "BB": "45", "SB": "5", "Dead_Ball": "10", "one_hit": 58}, {"name": "정경배", "team": "SK", "position": "2B", "avg": ".286", "obp": ".361", "slg": ".405", "total_hit": "122", "double_hit": "16", "triple_hit": "1", "home_run": "11", "BB": "44", "SB": "7", "Dead_Ball": "10", "one_hit": 94}, {"name": "박경완", "team": "SK", "position": "C", "avg": ".245", "obp": ".357", "slg": ".389", "total_hit": "85", "double_hit": "17", "triple_hit": "0", "home_run": "11", "BB": "57", "SB": "1", "Dead_Ball": "7", "one_hit": 57}, {"name": "김민재", "team": "SK", "position": "SS", "avg": ".277", "obp": ".346", "slg": ".334", "total_hit": "122", "double_hit": "19", "triple_hit": "0", "home_run": "2", "BB": "39", "SB": "20", "Dead_Ball": "9", "one_hit": 101}, {"name": "조중근", "team": "SK", "position": "CF", "avg": ".240", "obp": ".318", "slg": ".398", "total_hit": "41", "double_hit": "7", "triple_hit": "1", "home_run": "6", "BB": "11", "SB": "2", "Dead_Ball": "9", "one_hit": 27}, {"name": "최익성", "team": "SK", "position": "LF", "avg": ".214", "obp": ".333", "slg": ".429", "total_hit": "15", "double_hit": "1", "triple_hit": "1", "home_run": "4", "BB": "12", "SB": "3", "Dead_Ball": "1", "one_hit": 9}, {"name": "김태균", "team": "SK", "position": "3B", "avg": ".237", "obp": ".299", "slg": ".358", "total_hit": "55", "double_hit": "11", "triple_hit": "1", "home_run": "5", "BB": "18", "SB": "1", "Dead_Ball": "3", "one_hit": 38}, {"name": "채종범", "team": "SK", "position": "RF", "avg": ".556", "obp": ".636", "slg": ".667", "total_hit": "5", "double_hit": "1", "triple_hit": "0", "home_run": "0", "BB": "2", "SB": "0", "Dead_Ball": "0", "one_hit": 4}, {"name": "조원우", "team": "SK", "position": "LF", "avg": ".291", "obp": ".333", "slg": ".380", "total_hit": "23", "double_hit": "4", "triple_hit": "0", "home_run": "1", "BB": "5", "SB": "1", "Dead_Ball": "1", "one_hit": 18}, {"name": "강성우", "team": "SK", "position": "C", "avg": ".278", "obp": ".278", "slg": ".500", "total_hit": "5", "double_hit": "4", "triple_hit": "0", "home_run": "0", "BB": "0", "SB": "0", "Dead_Ball": "0", "one_hit": 1}, {"name": "최경철", "team": "SK", "position": "C", "avg": ".214", "obp": ".302", "slg": ".250", "total_hit": "12", "double_hit": "2", "triple_hit": "0", "home_run": "0", "BB": "6", "SB": "0", "Dead_Ball": "1", "one_hit": 10}, {"name": "이대수", "team": "SK", "position": "SS", "avg": ".203", "obp": ".288", "slg": ".288", "total_hit": "12", "double_hit": "3", "triple_hit": "1", "home_run": "0", "BB": "4", "SB": "1", "Dead_Ball": "3", "one_hit": 8}, {"name": "조경환", "team": "SK", "position": "LF", "avg": ".206", "obp": ".229", "slg": ".382", "total_hit": "7", "double_hit": "0", "triple_hit": "0", "home_run": "2", "BB": "0", "SB": "0", "Dead_Ball": "1", "one_hit": 5}, {"name": "김강민", "team": "SK", "position": "2B", "avg": ".225", "obp": ".296", "slg": ".250", "total_hit": "9", "double_hit": "1", "triple_hit": "0", "home_run": "0", "BB": "4", "SB": "2", "Dead_Ball": "0", "one_hit": 8}, {"name": "조동화", "team": "SK", "position": "LF", "avg": ".263", "obp": ".316", "slg": ".310", "total_hit": "74", "double_hit": "2", "triple_hit": "4", "home_run": "1", "BB": "19", "SB": "19", "Dead_Ball": "3", "one_hit": 67}, {"name": "박재상", "team": "SK", "position": "LF", "avg": ".130", "obp": ".184", "slg": ".152", "total_hit": "6", "double_hit": "1", "triple_hit": "0", "home_run": "0", "BB": "3", "SB": "3", "Dead_Ball": "0", "one_hit": 5}, {"name": "정근우", "team": "SK", "position": "3B", "avg": ".193", "obp": ".255", "slg": ".216", "total_hit": "17", "double_hit": "2", "triple_hit": "0", "home_run": "0", "BB": "4", "SB": "4", "Dead_Ball": "4", "one_hit": 15}, {"name": "김기태", "team": "SK", "position": "1B", "avg": ".205", "obp": ".297", "slg": ".241", "total_hit": "23", "double_hit": "4", "triple_hit": "0", "home_run": "0", "BB": "15", "SB": "0", "Dead_Ball": "0", "one_hit": 19}, {"name": "심정수", "team": "삼성", "position": "LF", "avg": ".275", "obp": ".402", "slg": ".501", "total_hit": "119", "double_hit": "14", "triple_hit": "0", "home_run": "28", "BB": "89", "SB": "3", "Dead_Ball": "4", "one_hit": 77}, {"name": "조동찬", "team": "삼성", "position": "3B", "avg": ".274", "obp": ".360", "slg": ".439", "total_hit": "106", "double_hit": "16", "triple_hit": "0", "home_run": "16", "BB": "39", "SB": "17", "Dead_Ball": "15", "one_hit": 74}, {"name": "박한이", "team": "삼성", "position": "CF", "avg": ".295", "obp": ".377", "slg": ".397", "total_hit": "139", "double_hit": "21", "triple_hit": "0", "home_run": "9", "BB": "55", "SB": "12", "Dead_Ball": "9", "one_hit": 109}, {"name": "진갑용", "team": "삼성", "position": "C", "avg": ".288", "obp": ".365", "slg": ".389", "total_hit": "100", "double_hit": "17", "triple_hit": "0", "home_run": "6", "BB": "36", "SB": "1", "Dead_Ball": "8", "one_hit": 77}, {"name": "김한수", "team": "삼성", "position": "1B", "avg": ".293", "obp": ".372", "slg": ".448", "total_hit": "119", "double_hit": "18", "triple_hit": "0", "home_run": "15", "BB": "35", "SB": "1", "Dead_Ball": "18", "one_hit": 86}, {"name": "박종호", "team": "삼성", "position": "2B", "avg": ".268", "obp": ".368", "slg": ".352", "total_hit": "105", "double_hit": "21", "triple_hit": "0", "home_run": "4", "BB": "46", "SB": "5", "Dead_Ball": "18", "one_hit": 80}, {"name": "박진만", "team": "삼성", "position": "SS", "avg": ".249", "obp": ".343", "slg": ".381", "total_hit": "70", "double_hit": "16", "triple_hit": "0", "home_run": "7", "BB": "32", "SB": "5", "Dead_Ball": "9", "one_hit": 47}, {"name": "양준혁", "team": "삼성", "position": "DH", "avg": ".261", "obp": ".367", "slg": ".404", "total_hit": "103", "double_hit": "15", "triple_hit": "1", "home_run": "13", "BB": "62", "SB": "10", "Dead_Ball": "5", "one_hit": 74}, {"name": "강동우", "team": "삼성", "position": "RF", "avg": ".240", "obp": ".322", "slg": ".346", "total_hit": "88", "double_hit": "15", "triple_hit": "3", "home_run": "6", "BB": "43", "SB": "9", "Dead_Ball": "3", "one_hit": 64}, {"name": "김종훈", "team": "삼성", "position": "LF", "avg": ".288", "obp": ".348", "slg": ".370", "total_hit": "42", "double_hit": "4", "triple_hit": "1", "home_run": "2", "BB": "11", "SB": "3", "Dead_Ball": "4", "one_hit": 35}, {"name": "강명구", "team": "삼성", "position": "CF", "avg": ".250", "obp": ".340", "slg": ".273", "total_hit": "11", "double_hit": "1", "triple_hit": "0", "home_run": "0", "BB": "4", "SB": "21", "Dead_Ball": "2", "one_hit": 10}, {"name": "김재걸", "team": "삼성", "position": "SS", "avg": ".247", "obp": ".311", "slg": ".290", "total_hit": "57", "double_hit": "7", "triple_hit": "0", "home_run": "1", "BB": "17", "SB": "8", "Dead_Ball": "5", "one_hit": 49}, {"name": "이정식", "team": "삼성", "position": "C", "avg": ".224", "obp": ".297", "slg": ".313", "total_hit": "15", "double_hit": "3", "triple_hit": "0", "home_run": "1", "BB": "6", "SB": "0", "Dead_Ball": "1", "one_hit": 11}, {"name": "조영훈", "team": "삼성", "position": "1B", "avg": ".250", "obp": ".400", "slg": ".500", "total_hit": "1", "double_hit": "1", "triple_hit": "0", "home_run": "0", "BB": "0", "SB": "0", "Dead_Ball": "1", "one_hit": 0}, {"name": "박정환", "team": "삼성", "position": "2B", "avg": ".184", "obp": ".256", "slg": ".289", "total_hit": "7", "double_hit": "1", "triple_hit": "0", "home_run": "1", "BB": "4", "SB": "1", "Dead_Ball": "0", "one_hit": 5}, {"name": "김영복", "team": "삼성", "position": "C", "avg": ".189", "obp": ".225", "slg": ".297", "total_hit": "7", "double_hit": "1", "triple_hit": "0", "home_run": "1", "BB": "2", "SB": "0", "Dead_Ball": "0", "one_hit": 5}, {"name": "손승현", "team": "삼성", "position": "C", "avg": ".000", "obp": ".000", "slg": ".000", "total_hit": "0", "double_hit": "0", "triple_hit": "0", "home_run": "0", "BB": "0", "SB": "0", "Dead_Ball": "0", "one_hit": 0}, {"name": "신동주", "team": "삼성", "position": "RF", "avg": ".000", "obp": ".200", "slg": ".000", "total_hit": "0", "double_hit": "0", "triple_hit": "0", "home_run": "0", "BB": "1", "SB": "0", "Dead_Ball": "1", "one_hit": 0}, {"name": "데이비스", "team": "한화", "position": "CF", "avg": ".323", "obp": ".412", "slg": ".545", "total_hit": "139", "double_hit": "24", "triple_hit": "0", "home_run": "24", "BB": "65", "SB": "7", "Dead_Ball": "5", "one_hit": 91}, {"name": "김태균", "team": "한화", "position": "1B", "avg": ".317", "obp": ".401", "slg": ".547", "total_hit": "146", "double_hit": "33", "triple_hit": "2", "home_run": "23", "BB": "60", "SB": "3", "Dead_Ball": "6", "one_hit": 88}, {"name": "이범호", "team": "한화", "position": "3B", "avg": ".273", "obp": ".357", "slg": ".514", "total_hit": "121", "double_hit": "27", "triple_hit": "1", "home_run": "26", "BB": "53", "SB": "6", "Dead_Ball": "9", "one_hit": 67}, {"name": "브리또", "team": "한화", "position": "SS", "avg": ".286", "obp": ".328", "slg": ".512", "total_hit": "82", "double_hit": "14", "triple_hit": "0", "home_run": "17", "BB": "11", "SB": "0", "Dead_Ball": "8", "one_hit": 51}, {"name": "신경현", "team": "한화", "position": "C", "avg": ".277", "obp": ".338", "slg": ".368", "total_hit": "89", "double_hit": "15", "triple_hit": "1", "home_run": "4", "BB": "29", "SB": "2", "Dead_Ball": "2", "one_hit": 69}, {"name": "조원우", "team": "한화", "position": "LF", "avg": ".305", "obp": ".371", "slg": ".415", "total_hit": "83", "double_hit": "13", "triple_hit": "1", "home_run": "5", "BB": "26", "SB": "6", "Dead_Ball": "3", "one_hit": 64}, {"name": "이도형", "team": "한화", "position": "DH", "avg": ".258", "obp": ".325", "slg": ".478", "total_hit": "101", "double_hit": "18", "triple_hit": "1", "home_run": "22", "BB": "30", "SB": "0", "Dead_Ball": "9", "one_hit": 60}, {"name": "김인철", "team": "한화", "position": "RF", "avg": ".275", "obp": ".330", "slg": ".450", "total_hit": "72", "double_hit": "16", "triple_hit": "0", "home_run": "10", "BB": "20", "SB": "8", "Dead_Ball": "2", "one_hit": 46}, {"name": "백재호", "team": "한화", "position": "2B", "avg": ".277", "obp": ".329", "slg": ".362", "total_hit": "65", "double_hit": "8", "triple_hit": "0", "home_run": "4", "BB": "15", "SB": "5", "Dead_Ball": "4", "one_hit": 53}, {"name": "심광호", "team": "한화", "position": "C", "avg": ".265", "obp": ".290", "slg": ".500", "total_hit": "27", "double_hit": "3", "triple_hit": "0", "home_run": "7", "BB": "1", "SB": "1", "Dead_Ball": "3", "one_hit": 17}, {"name": "고동진", "team": "한화", "position": "RF", "avg": ".200", "obp": ".308", "slg": ".292", "total_hit": "50", "double_hit": "14", "triple_hit": "0", "home_run": "3", "BB": "23", "SB": "11", "Dead_Ball": "16", "one_hit": 33}, {"name": "임수민", "team": "한화", "position": "2B", "avg": ".234", "obp": ".265", "slg": ".369", "total_hit": "26", "double_hit": "6", "triple_hit": "0", "home_run": "3", "BB": "6", "SB": "1", "Dead_Ball": "0", "one_hit": 17}, {"name": "김수연", "team": "한화", "position": "LF", "avg": ".253", "obp": ".305", "slg": ".304", "total_hit": "69", "double_hit": "10", "triple_hit": "2", "home_run": "0", "BB": "20", "SB": "9", "Dead_Ball": "1", "one_hit": 57}, {"name": "한상훈", "team": "한화", "position": "2B", "avg": ".214", "obp": ".287", "slg": ".268", "total_hit": "36", "double_hit": "4", "triple_hit": "1", "home_run": "1", "BB": "17", "SB": "1", "Dead_Ball": "0", "one_hit": 30}, {"name": "고지행", "team": "한화", "position": "2B", "avg": ".231", "obp": ".254", "slg": ".323", "total_hit": "15", "double_hit": "0", "triple_hit": "0", "home_run": "2", "BB": "1", "SB": "0", "Dead_Ball": "1", "one_hit": 13}, {"name": "장종훈", "team": "한화", "position": "1B", "avg": ".091", "obp": ".091", "slg": ".364", "total_hit": "1", "double_hit": "0", "triple_hit": "0", "home_run": "1", "BB": "0", "SB": "0", "Dead_Ball": "0", "one_hit": 0}, {"name": "박노민", "team": "한화", "position": "C", "avg": ".100", "obp": ".100", "slg": ".100", "total_hit": "1", "double_hit": "0", "triple_hit": "0", "home_run": "0", "BB": "0", "SB": "0", "Dead_Ball": "0", "one_hit": 1}, {"name": "백승룡", "team": "한화", "position": "SS", "avg": ".127", "obp": ".253", "slg": ".159", "total_hit": "8", "double_hit": "2", "triple_hit": "0", "home_run": "0", "BB": "7", "SB": "1", "Dead_Ball": "4", "one_hit": 6}, {"name": "이병규", "team": "LG", "position": "CF", "avg": ".337", "obp": ".388", "slg": ".455", "total_hit": "157", "double_hit": "24", "triple_hit": "2", "home_run": "9", "BB": "34", "SB": "10", "Dead_Ball": "9", "one_hit": 122}, {"name": "클리어", "team": "LG", "position": "RF", "avg": ".303", "obp": ".371", "slg": ".493", "total_hit": "122", "double_hit": "23", "triple_hit": "4", "home_run": "15", "BB": "36", "SB": "19", "Dead_Ball": "10", "one_hit": 80}, {"name": "박용택", "team": "LG", "position": "LF", "avg": ".280", "obp": ".344", "slg": ".432", "total_hit": "132", "double_hit": "25", "triple_hit": "1", "home_run": "15", "BB": "43", "SB": "43", "Dead_Ball": "5", "one_hit": 91}, {"name": "이성열", "team": "LG", "position": "C", "avg": ".235", "obp": ".374", "slg": ".449", "total_hit": "44", "double_hit": "7", "triple_hit": "3", "home_run": "9", "BB": "21", "SB": "3", "Dead_Ball": "21", "one_hit": 25}, {"name": "최동수", "team": "LG", "position": "1B", "avg": ".319", "obp": ".368", "slg": ".486", "total_hit": "67", "double_hit": "17", "triple_hit": "0", "home_run": "6", "BB": "17", "SB": "1", "Dead_Ball": "0", "one_hit": 44}, {"name": "이종열", "team": "LG", "position": "2B", "avg": ".253", "obp": ".314", "slg": ".361", "total_hit": "68", "double_hit": "7", "triple_hit": "2", "home_run": "6", "BB": "21", "SB": "5", "Dead_Ball": "4", "one_hit": 53}, {"name": "김정민", "team": "LG", "position": "C", "avg": ".274", "obp": ".318", "slg": ".403", "total_hit": "51", "double_hit": "9", "triple_hit": "0", "home_run": "5", "BB": "7", "SB": "0", "Dead_Ball": "6", "one_hit": 37}, {"name": "박기남", "team": "LG", "position": "3B", "avg": ".272", "obp": ".369", "slg": ".375", "total_hit": "37", "double_hit": "2", "triple_hit": "0", "home_run": "4", "BB": "19", "SB": "0", "Dead_Ball": "2", "one_hit": 31}, {"name": "이대형", "team": "LG", "position": "CF", "avg": ".268", "obp": ".331", "slg": ".315", "total_hit": "34", "double_hit": "4", "triple_hit": "1", "home_run": "0", "BB": "11", "SB": "37", "Dead_Ball": "1", "one_hit": 29}, {"name": "권용관", "team": "LG", "position": "SS", "avg": ".237", "obp": ".272", "slg": ".443", "total_hit": "46", "double_hit": "7", "triple_hit": "3", "home_run": "9", "BB": "7", "SB": "3", "Dead_Ball": "3", "one_hit": 27}, {"name": "조인성", "team": "LG", "position": "C", "avg": ".224", "obp": ".285", "slg": ".368", "total_hit": "45", "double_hit": "11", "triple_hit": "0", "home_run": "6", "BB": "14", "SB": "0", "Dead_Ball": "4", "one_hit": 28}, {"name": "한규식", "team": "LG", "position": "SS", "avg": ".236", "obp": ".324", "slg": ".276", "total_hit": "65", "double_hit": "9", "triple_hit": "1", "home_run": "0", "BB": "36", "SB": "0", "Dead_Ball": "1", "one_hit": 55}, {"name": "정의윤", "team": "LG", "position": "LF", "avg": ".242", "obp": ".288", "slg": ".369", "total_hit": "76", "double_hit": "10", "triple_hit": "3", "home_run": "8", "BB": "17", "SB": "3", "Dead_Ball": "4", "one_hit": 55}, {"name": "박병호", "team": "LG", "position": "C", "avg": ".190", "obp": ".265", "slg": ".313", "total_hit": "31", "double_hit": "11", "triple_hit": "0", "home_run": "3", "BB": "12", "SB": "1", "Dead_Ball": "6", "one_hit": 17}, {"name": "최승환", "team": "LG", "position": "C", "avg": ".269", "obp": ".296", "slg": ".462", "total_hit": "7", "double_hit": "2", "triple_hit": "0", "home_run": "1", "BB": "1", "SB": "0", "Dead_Ball": "0", "one_hit": 4}, {"name": "안재만", "team": "LG", "position": "3B", "avg": ".236", "obp": ".290", "slg": ".328", "total_hit": "41", "double_hit": "10", "triple_hit": "0", "home_run": "2", "BB": "9", "SB": "15", "Dead_Ball": "5", "one_hit": 29}, {"name": "안상준", "team": "LG", "position": "2B", "avg": ".206", "obp": ".270", "slg": ".265", "total_hit": "14", "double_hit": "4", "triple_hit": "0", "home_run": "0", "BB": "5", "SB": "2", "Dead_Ball": "1", "one_hit": 10}, {"name": "김태완", "team": "LG", "position": "2B", "avg": ".100", "obp": ".265", "slg": ".100", "total_hit": "4", "double_hit": "0", "triple_hit": "0", "home_run": "0", "BB": "7", "SB": "0", "Dead_Ball": "2", "one_hit": 4}, {"name": "서용빈", "team": "LG", "position": "1B", "avg": ".128", "obp": ".150", "slg": ".205", "total_hit": "5", "double_hit": "1", "triple_hit": "1", "home_run": "0", "BB": "1", "SB": "0", "Dead_Ball": "0", "one_hit": 3}, {"name": "이대호", "team": "롯데", "position": "3B", "avg": ".266", "obp": ".354", "slg": ".452", "total_hit": "119", "double_hit": "16", "triple_hit": "2", "home_run": "21", "BB": "47", "SB": "1", "Dead_Ball": "15", "one_hit": 80}, {"name": "펠로우", "team": "롯데", "position": "RF", "avg": ".284", "obp": ".348", "slg": ".500", "total_hit": "113", "double_hit": "15", "triple_hit": "1", "home_run": "23", "BB": "30", "SB": "3", "Dead_Ball": "11", "one_hit": 74}, {"name": "정수근", "team": "롯데", "position": "CF", "avg": ".286", "obp": ".374", "slg": ".354", "total_hit": "106", "double_hit": "21", "triple_hit": "2", "home_run": "0", "BB": "49", "SB": "21", "Dead_Ball": "4", "one_hit": 83}, {"name": "박기혁", "team": "롯데", "position": "SS", "avg": ".278", "obp": ".349", "slg": ".361", "total_hit": "93", "double_hit": "13", "triple_hit": "3", "home_run": "3", "BB": "36", "SB": "8", "Dead_Ball": "1", "one_hit": 74}, {"name": "라이온", "team": "롯데", "position": "1B", "avg": ".268", "obp": ".321", "slg": ".429", "total_hit": "132", "double_hit": "40", "triple_hit": "3", "home_run": "11", "BB": "37", "SB": "7", "Dead_Ball": "2", "one_hit": 78}, {"name": "최준석", "team": "롯데", "position": "C", "avg": ".246", "obp": ".312", "slg": ".361", "total_hit": "69", "double_hit": "8", "triple_hit": "0", "home_run": "8", "BB": "24", "SB": "4", "Dead_Ball": "3", "one_hit": 53}, {"name": "신명철", "team": "롯데", "position": "2B", "avg": ".256", "obp": ".311", "slg": ".363", "total_hit": "88", "double_hit": "16", "triple_hit": "3", "home_run": "5", "BB": "25", "SB": "21", "Dead_Ball": "3", "one_hit": 64}, {"name": "박연수", "team": "롯데", "position": "LF", "avg": ".281", "obp": ".353", "slg": ".421", "total_hit": "48", "double_hit": "9", "triple_hit": "0", "home_run": "5", "BB": "15", "SB": "1", "Dead_Ball": "4", "one_hit": 34}, {"name": "강민호", "team": "롯데", "position": "C", "avg": ".243", "obp": ".267", "slg": ".341", "total_hit": "52", "double_hit": "11", "triple_hit": "2", "home_run": "2", "BB": "5", "SB": "1", "Dead_Ball": "2", "one_hit": 37}, {"name": "손인호", "team": "롯데", "position": "LF", "avg": ".241", "obp": ".312", "slg": ".322", "total_hit": "83", "double_hit": "16", "triple_hit": "3", "home_run": "2", "BB": "29", "SB": "3", "Dead_Ball": "7", "one_hit": 62}, {"name": "이동훈", "team": "롯데", "position": "C", "avg": ".667", "obp": ".667", "slg": "1.000", "total_hit": "2", "double_hit": "1", "triple_hit": "0", "home_run": "0", "BB": "0", "SB": "0", "Dead_Ball": "0", "one_hit": 1}, {"name": "조인신", "team": "롯데", "position": "SS", "avg": ".222", "obp": ".241", "slg": ".296", "total_hit": "6", "double_hit": "2", "triple_hit": "0", "home_run": "0", "BB": "1", "SB": "1", "Dead_Ball": "0", "one_hit": 4}, {"name": "김승관", "team": "롯데", "position": "1B", "avg": ".143", "obp": ".368", "slg": ".143", "total_hit": "2", "double_hit": "0", "triple_hit": "0", "home_run": "0", "BB": "5", "SB": "0", "Dead_Ball": "0", "one_hit": 2}, {"name": "박현승", "team": "롯데", "position": "2B", "avg": ".211", "obp": ".302", "slg": ".237", "total_hit": "8", "double_hit": "1", "triple_hit": "0", "home_run": "0", "BB": "5", "SB": "1", "Dead_Ball": "0", "one_hit": 7}, {"name": "최기문", "team": "롯데", "position": "C", "avg": ".192", "obp": ".280", "slg": ".243", "total_hit": "34", "double_hit": "7", "triple_hit": "1", "home_run": "0", "BB": "13", "SB": "3", "Dead_Ball": "9", "one_hit": 26}, {"name": "박경진", "team": "롯데", "position": "C", "avg": ".167", "obp": ".167", "slg": ".167", "total_hit": "2", "double_hit": "0", "triple_hit": "0", "home_run": "0", "BB": "0", "SB": "0", "Dead_Ball": "0", "one_hit": 2}, {"name": "이원석", "team": "롯데", "position": "3B", "avg": ".202", "obp": ".294", "slg": ".294", "total_hit": "33", "double_hit": "10", "triple_hit": "1", "home_run": "1", "BB": "18", "SB": "0", "Dead_Ball": "4", "one_hit": 21}, {"name": "박준서", "team": "롯데", "position": "SS", "avg": ".195", "obp": ".233", "slg": ".244", "total_hit": "16", "double_hit": "2", "triple_hit": "1", "home_run": "0", "BB": "4", "SB": "4", "Dead_Ball": "0", "one_hit": 13}, {"name": "이종범", "team": "KIA", "position": "CF", "avg": ".312", "obp": ".393", "slg": ".421", "total_hit": "134", "double_hit": "25", "triple_hit": "2", "home_run": "6", "BB": "47", "SB": "28", "Dead_Ball": "11", "one_hit": 101}, {"name": "장성호", "team": "KIA", "position": "1B", "avg": ".300", "obp": ".382", "slg": ".457", "total_hit": "139", "double_hit": "23", "triple_hit": "1", "home_run": "16", "BB": "61", "SB": "4", "Dead_Ball": "3", "one_hit": 99}, {"name": "홍세완", "team": "KIA", "position": "SS", "avg": ".284", "obp": ".353", "slg": ".412", "total_hit": "98", "double_hit": "15", "triple_hit": "1", "home_run": "9", "BB": "36", "SB": "7", "Dead_Ball": "2", "one_hit": 73}, {"name": "손지환", "team": "KIA", "position": "3B", "avg": ".278", "obp": ".344", "slg": ".424", "total_hit": "88", "double_hit": "13", "triple_hit": "0", "home_run": "11", "BB": "24", "SB": "1", "Dead_Ball": "9", "one_hit": 64}, {"name": "심재학", "team": "KIA", "position": "RF", "avg": ".254", "obp": ".373", "slg": ".433", "total_hit": "64", "double_hit": "9", "triple_hit": "0", "home_run": "12", "BB": "43", "SB": "3", "Dead_Ball": "7", "one_hit": 43}, {"name": "이용규", "team": "KIA", "position": "RF", "avg": ".266", "obp": ".340", "slg": ".353", "total_hit": "110", "double_hit": "17", "triple_hit": "2", "home_run": "5", "BB": "39", "SB": "31", "Dead_Ball": "9", "one_hit": 86}, {"name": "마해영", "team": "KIA", "position": "DH", "avg": ".266", "obp": ".346", "slg": ".423", "total_hit": "90", "double_hit": "17", "triple_hit": "0", "home_run": "12", "BB": "35", "SB": "0", "Dead_Ball": "8", "one_hit": 61}, {"name": "김상훈", "team": "KIA", "position": "C", "avg": ".235", "obp": ".297", "slg": ".342", "total_hit": "70", "double_hit": "8", "triple_hit": "0", "home_run": "8", "BB": "24", "SB": "0", "Dead_Ball": "4", "one_hit": 54}, {"name": "김종국", "team": "KIA", "position": "2B", "avg": ".235", "obp": ".306", "slg": ".324", "total_hit": "88", "double_hit": "15", "triple_hit": "3", "home_run": "4", "BB": "37", "SB": "11", "Dead_Ball": "3", "one_hit": 66}, {"name": "송산", "team": "KIA", "position": "C", "avg": ".264", "obp": ".324", "slg": ".368", "total_hit": "33", "double_hit": "4", "triple_hit": "0", "home_run": "3", "BB": "10", "SB": "2", "Dead_Ball": "1", "one_hit": 26}, {"name": "이재주", "team": "KIA", "position": "DH", "avg": ".250", "obp": ".372", "slg": ".435", "total_hit": "31", "double_hit": "8", "triple_hit": "0", "home_run": "5", "BB": "22", "SB": "0", "Dead_Ball": "2", "one_hit": 18}, {"name": "김경언", "team": "KIA", "position": "LF", "avg": ".271", "obp": ".308", "slg": ".415", "total_hit": "51", "double_hit": "10", "triple_hit": "1", "home_run": "5", "BB": "8", "SB": "2", "Dead_Ball": "2", "one_hit": 35}, {"name": "김민철", "team": "KIA", "position": "SS", "avg": ".218", "obp": ".271", "slg": ".291", "total_hit": "39", "double_hit": "7", "triple_hit": "3", "home_run": "0", "BB": "10", "SB": "11", "Dead_Ball": "3", "one_hit": 29}, {"name": "김성호", "team": "KIA", "position": "C", "avg": ".000", "obp": ".000", "slg": ".000", "total_hit": "0", "double_hit": "0", "triple_hit": "0", "home_run": "0", "BB": "0", "SB": "0", "Dead_Ball": "0", "one_hit": 0}, {"name": "차일목", "team": "KIA", "position": "C", "avg": ".250", "obp": ".333", "slg": ".250", "total_hit": "2", "double_hit": "0", "triple_hit": "0", "home_run": "0", "BB": "1", "SB": "0", "Dead_Ball": "0", "one_hit": 2}, {"name": "주창훈", "team": "KIA", "position": "1B", "avg": ".000", "obp": ".333", "slg": ".000", "total_hit": "0", "double_hit": "0", "triple_hit": "0", "home_run": "0", "BB": "0", "SB": "0", "Dead_Ball": "1", "one_hit": 0}, {"name": "홍현우", "team": "KIA", "position": "3B", "avg": ".220", "obp": ".258", "slg": ".322", "total_hit": "13", "double_hit": "3", "triple_hit": "0", "home_run": "1", "BB": "3", "SB": "0", "Dead_Ball": "0", "one_hit": 9}, {"name": "신동주", "team": "KIA", "position": "CF", "avg": ".125", "obp": ".160", "slg": ".125", "total_hit": "3", "double_hit": "0", "triple_hit": "0", "home_run": "0", "BB": "0", "SB": "0", "Dead_Ball": "1", "one_hit": 3}, {"name": "김동주", "team": "두산", "position": "3B", "avg": ".302", "obp": ".444", "slg": ".470", "total_hit": "81", "double_hit": "13", "triple_hit": "1", "home_run": "10", "BB": "57", "SB": "1", "Dead_Ball": "12", "one_hit": 57}, {"name": "손시헌", "team": "두산", "position": "SS", "avg": ".276", "obp": ".352", "slg": ".373", "total_hit": "115", "double_hit": "18", "triple_hit": "5", "home_run": "4", "BB": "48", "SB": "2", "Dead_Ball": "4", "one_hit": 88}, {"name": "안경현", "team": "두산", "position": "2B", "avg": ".293", "obp": ".382", "slg": ".380", "total_hit": "104", "double_hit": "19", "triple_hit": "0", "home_run": "4", "BB": "44", "SB": "1", "Dead_Ball": "9", "one_hit": 81}, {"name": "홍성흔", "team": "두산", "position": "C", "avg": ".272", "obp": ".324", "slg": ".398", "total_hit": "107", "double_hit": "17", "triple_hit": "0", "home_run": "11", "BB": "29", "SB": "2", "Dead_Ball": "3", "one_hit": 79}, {"name": "임재철", "team": "두산", "position": "RF", "avg": ".310", "obp": ".377", "slg": ".393", "total_hit": "104", "double_hit": "13", "triple_hit": "3", "home_run": "3", "BB": "35", "SB": "10", "Dead_Ball": "4", "one_hit": 85}, {"name": "김창희", "team": "두산", "position": "CF", "avg": ".271", "obp": ".379", "slg": ".353", "total_hit": "60", "double_hit": "9", "triple_hit": "0", "home_run": "3", "BB": "35", "SB": "4", "Dead_Ball": "5", "one_hit": 48}, {"name": "문희성", "team": "두산", "position": "DH", "avg": ".273", "obp": ".353", "slg": ".413", "total_hit": "88", "double_hit": "15", "triple_hit": "0", "home_run": "10", "BB": "29", "SB": "12", "Dead_Ball": "13", "one_hit": 63}, {"name": "장원진", "team": "두산", "position": "1B", "avg": ".286", "obp": ".361", "slg": ".345", "total_hit": "121", "double_hit": "16", "triple_hit": "0", "home_run": "3", "BB": "42", "SB": "4", "Dead_Ball": "9", "one_hit": 102}, {"name": "최경환", "team": "두산", "position": "LF", "avg": ".262", "obp": ".333", "slg": ".352", "total_hit": "87", "double_hit": "17", "triple_hit": "2", "home_run": "3", "BB": "32", "SB": "11", "Dead_Ball": "6", "one_hit": 65}, {"name": "전상렬", "team": "두산", "position": "CF", "avg": ".241", "obp": ".316", "slg": ".305", "total_hit": "75", "double_hit": "15", "triple_hit": "1", "home_run": "1", "BB": "32", "SB": "3", "Dead_Ball": "2", "one_hit": 58}, {"name": "홍원기", "team": "두산", "position": "3B", "avg": ".230", "obp": ".317", "slg": ".353", "total_hit": "32", "double_hit": "6", "triple_hit": "1", "home_run": "3", "BB": "13", "SB": "0", "Dead_Ball": "5", "one_hit": 22}, {"name": "나주환", "team": "두산", "position": "3B", "avg": ".270", "obp": ".321", "slg": ".339", "total_hit": "47", "double_hit": "9", "triple_hit": "0", "home_run": "1", "BB": "10", "SB": "8", "Dead_Ball": "4", "one_hit": 37}, {"name": "황윤성", "team": "두산", "position": "1B", "avg": ".244", "obp": ".343", "slg": ".370", "total_hit": "29", "double_hit": "4", "triple_hit": "1", "home_run": "3", "BB": "15", "SB": "0", "Dead_Ball": "3", "one_hit": 21}, {"name": "강봉규", "team": "두산", "position": "LF", "avg": ".235", "obp": ".361", "slg": ".314", "total_hit": "24", "double_hit": "3", "triple_hit": "1", "home_run": "1", "BB": "18", "SB": "2", "Dead_Ball": "2", "one_hit": 19}, {"name": "강인권", "team": "두산", "position": "C", "avg": ".286", "obp": ".412", "slg": ".321", "total_hit": "8", "double_hit": "1", "triple_hit": "0", "home_run": "0", "BB": "5", "SB": "0", "Dead_Ball": "1", "one_hit": 7}, {"name": "용덕한", "team": "두산", "position": "C", "avg": ".238", "obp": ".293", "slg": ".277", "total_hit": "31", "double_hit": "5", "triple_hit": "0", "home_run": "0", "BB": "10", "SB": "1", "Dead_Ball": "0", "one_hit": 26}, {"name": "이대현", "team": "두산", "position": "C", "avg": ".000", "obp": ".000", "slg": ".000", "total_hit": "0", "double_hit": "0", "triple_hit": "0", "home_run": "0", "BB": "0", "SB": "0", "Dead_Ball": "0", "one_hit": 0}, {"name": "정원석", "team": "두산", "position": "2B", "avg": ".154", "obp": ".267", "slg": ".154", "total_hit": "2", "double_hit": "0", "triple_hit": "0", "home_run": "0", "BB": "2", "SB": "1", "Dead_Ball": "0", "one_hit": 2}, {"name": "윤승균", "team": "두산", "position": "CF", "avg": ".189", "obp": ".232", "slg": ".244", "total_hit": "17", "double_hit": "2", "triple_hit": "0", "home_run": "1", "BB": "5", "SB": "39", "Dead_Ball": "0", "one_hit": 14}, {"name": "서튼", "team": "현대", "position": "LF", "avg": ".292", "obp": ".411", "slg": ".592", "total_hit": "124", "double_hit": "18", "triple_hit": "2", "home_run": "35", "BB": "86", "SB": "0", "Dead_Ball": "4", "one_hit": 69}, {"name": "송지만", "team": "현대", "position": "RF", "avg": ".271", "obp": ".366", "slg": ".486", "total_hit": "118", "double_hit": "22", "triple_hit": "0", "home_run": "24", "BB": "43", "SB": "3", "Dead_Ball": "24", "one_hit": 72}, {"name": "정성훈", "team": "현대", "position": "3B", "avg": ".266", "obp": ".346", "slg": ".426", "total_hit": "122", "double_hit": "20", "triple_hit": "1", "home_run": "17", "BB": "49", "SB": "7", "Dead_Ball": "7", "one_hit": 84}, {"name": "강귀태", "team": "현대", "position": "C", "avg": ".264", "obp": ".338", "slg": ".400", "total_hit": "70", "double_hit": "12", "triple_hit": "0", "home_run": "8", "BB": "26", "SB": "2", "Dead_Ball": "4", "one_hit": 50}, {"name": "정수성", "team": "현대", "position": "CF", "avg": ".273", "obp": ".344", "slg": ".339", "total_hit": "100", "double_hit": "14", "triple_hit": "5", "home_run": "0", "BB": "21", "SB": "29", "Dead_Ball": "20", "one_hit": 81}, {"name": "이택근", "team": "현대", "position": "1B", "avg": ".331", "obp": ".440", "slg": ".439", "total_hit": "46", "double_hit": "9", "triple_hit": "0", "home_run": "2", "BB": "19", "SB": "2", "Dead_Ball": "8", "one_hit": 35}, {"name": "이숭용", "team": "현대", "position": "DH", "avg": ".252", "obp": ".357", "slg": ".418", "total_hit": "83", "double_hit": "13", "triple_hit": "0", "home_run": "14", "BB": "46", "SB": "1", "Dead_Ball": "9", "one_hit": 56}, {"name": "서한규", "team": "현대", "position": "SS", "avg": ".248", "obp": ".336", "slg": ".319", "total_hit": "63", "double_hit": "8", "triple_hit": "2", "home_run": "2", "BB": "29", "SB": "9", "Dead_Ball": "5", "one_hit": 51}, {"name": "강병식", "team": "현대", "position": "LF", "avg": ".247", "obp": ".357", "slg": ".401", "total_hit": "45", "double_hit": "10", "triple_hit": "0", "home_run": "6", "BB": "27", "SB": "2", "Dead_Ball": "4", "one_hit": 29}, {"name": "전준호", "team": "현대", "position": "CF", "avg": ".266", "obp": ".332", "slg": ".309", "total_hit": "74", "double_hit": "8", "triple_hit": "2", "home_run": "0", "BB": "25", "SB": "18", "Dead_Ball": "4", "one_hit": 64}, {"name": "김동수", "team": "현대", "position": "C", "avg": ".219", "obp": ".283", "slg": ".358", "total_hit": "60", "double_hit": "4", "triple_hit": "2", "home_run": "10", "BB": "20", "SB": "2", "Dead_Ball": "5", "one_hit": 44}, {"name": "채종국", "team": "현대", "position": "2B", "avg": ".237", "obp": ".320", "slg": ".351", "total_hit": "81", "double_hit": "10", "triple_hit": "1", "home_run": "9", "BB": "25", "SB": "1", "Dead_Ball": "19", "one_hit": 61}, {"name": "김일경", "team": "현대", "position": "3B", "avg": ".228", "obp": ".339", "slg": ".317", "total_hit": "23", "double_hit": "4", "triple_hit": "1", "home_run": "1", "BB": "15", "SB": "4", "Dead_Ball": "2", "one_hit": 17}, {"name": "전근표", "team": "현대", "position": "RF", "avg": ".208", "obp": ".315", "slg": ".344", "total_hit": "20", "double_hit": "7", "triple_hit": "0", "home_run": "2", "BB": "14", "SB": "0", "Dead_Ball": "1", "one_hit": 11}, {"name": "오재일", "team": "현대", "position": "1B", "avg": ".000", "obp": ".000", "slg": ".000", "total_hit": "0", "double_hit": "0", "triple_hit": "0", "home_run": "0", "BB": "0", "SB": "0", "Dead_Ball": "0", "one_hit": 0}, {"name": "허준", "team": "현대", "position": "C", "avg": "", "obp": "", "slg": "", "total_hit": "0", "double_hit": "0", "triple_hit": "0", "home_run": "0", "BB": "0", "SB": "0", "Dead_Ball": "0", "one_hit": 0}, {"name": "지석훈", "team": "현대", "position": "SS", "avg": ".179", "obp": ".209", "slg": ".264", "total_hit": "19", "double_hit": "3", "triple_hit": "0", "home_run": "2", "BB": "3", "SB": "0", "Dead_Ball": "1", "one_hit": 14}]